wirelesssgx/__init__.py
wirelesssgx/__main__.py
wirelesssgx/app.py
wirelesssgx/cli.py
wirelesssgx/core.py
wirelesssgx/network.py
wirelesssgx/storage.py
wirelesssgx/screens/__init__.py
wirelesssgx/screens/autoconnect.py
wirelesssgx/screens/credentials.py
wirelesssgx/screens/otp.py
wirelesssgx/screens/register.py
wirelesssgx/screens/success.py
wirelesssgx/screens/welcome.py
wirelesssgx-1.0.22.dist-info/licenses/LICENSE
wirelesssgx-1.0.22.dist-info/METADATA
wirelesssgx-1.0.22.dist-info/WHEEL
wirelesssgx-1.0.22.dist-info/entry_points.txt
wirelesssgx-1.0.22.dist-info/top_level.txt
wirelesssgx-1.0.22.dist-info/RECORD
