Metadata-Version: 2.4
Name: wirelesssgx
Version: 1.0.22
Summary: A modern TUI for Wireless@SGx setup on Linux
Home-page: https://github.com/siva-sub/wireless-sgx-linux-tui
Author: Sivasubramanian Ramanathan
Author-email: Sivasubramanian Ramanathan <hello@sivasub.com>
Maintainer-email: Sivasubramanian Ramanathan <hello@sivasub.com>
License: MIT License
Project-URL: Homepage, https://github.com/siva-sub/wireless-sgx-linux-tui
Project-URL: Repository, https://github.com/siva-sub/wireless-sgx-linux-tui
Project-URL: Issues, https://github.com/siva-sub/wireless-sgx-linux-tui/issues
Keywords: wireless,singapore,wifi,tui,linux,networking
Classifier: Development Status :: 4 - Beta
Classifier: Environment :: Console
Classifier: Intended Audience :: End Users/Desktop
Classifier: License :: OSI Approved :: MIT License
Classifier: Operating System :: POSIX :: Linux
Classifier: Programming Language :: Python :: 3
Classifier: Programming Language :: Python :: 3.8
Classifier: Programming Language :: Python :: 3.9
Classifier: Programming Language :: Python :: 3.10
Classifier: Programming Language :: Python :: 3.11
Classifier: Programming Language :: Python :: 3.12
Classifier: Topic :: System :: Networking
Classifier: Topic :: Utilities
Requires-Python: >=3.8
License-File: LICENSE
Requires-Dist: textual>=0.41.0
Requires-Dist: pycryptodome>=3.19.0
Requires-Dist: keyring>=24.0.0
Requires-Dist: python-dateutil>=2.8.2
Requires-Dist: requests>=2.31.0
Requires-Dist: click>=8.1.7
Requires-Dist: cryptography>=41.0.0
Provides-Extra: dev
Requires-Dist: pytest>=7.0.0; extra == "dev"
Requires-Dist: pytest-asyncio>=0.21.0; extra == "dev"
Requires-Dist: black>=23.0.0; extra == "dev"
Requires-Dist: flake8>=6.0.0; extra == "dev"
Requires-Dist: build>=0.10.0; extra == "dev"
Requires-Dist: twine>=4.0.0; extra == "dev"
Dynamic: author
Dynamic: home-page
Dynamic: license-file
Dynamic: requires-python
